crypto_balancer/__init__.py
crypto_balancer/backtest_exchange.py
crypto_balancer/backtester.py
crypto_balancer/ccxt_exchange.py
crypto_balancer/dummy_exchange.py
crypto_balancer/executor.py
crypto_balancer/main.py
crypto_balancer/order.py
crypto_balancer/portfolio.py
crypto_balancer/simple_balancer.py
crypto_balancer/tests.py
crypto_balancer-3.1.1.dist-info/LICENSE
crypto_balancer-3.1.1.dist-info/METADATA
crypto_balancer-3.1.1.dist-info/WHEEL
crypto_balancer-3.1.1.dist-info/entry_points.txt
crypto_balancer-3.1.1.dist-info/top_level.txt
crypto_balancer-3.1.1.dist-info/RECORD
