Metadata-Version: 2.1
Name: crypto-balancer
Version: 3.1.1
Summary: A tool to automatically balance cryptocurrency portfolios
Home-page: https://github.com/hammertoe/crypto_balancer
Author: Matt Hamilton
Author-email: mh@quernus.co.uk
License: MIT
Download-URL: https://github.com/hammertoe/crypto_balancer/archive/3.1.1.tar.gz
Keywords: cryptocurrency,portfolio,xrp,ethereum,bitcoin,btc,eth
Platform: UNKNOWN
Classifier: Development Status :: 5 - Production/Stable
Classifier: Intended Audience :: End Users/Desktop
Classifier: Intended Audience :: Financial and Insurance Industry
Classifier: Topic :: Office/Business :: Financial :: Investment
Classifier: License :: OSI Approved :: MIT License
Classifier: Programming Language :: Python :: 3
Classifier: Programming Language :: Python :: 3.6
Requires-Dist: ccxt
